monitor/__init__.py
monitor/performance.py
monitor/security.py
monitor/seo.py
monitor/ui.py
report/__init__.py
report/pdf_report.py
report/xlsx_report.py
DashboardServerReportWebsiteSide-0.1.0.dist-info/METADATA
DashboardServerReportWebsiteSide-0.1.0.dist-info/WHEEL
DashboardServerReportWebsiteSide-0.1.0.dist-info/top_level.txt
DashboardServerReportWebsiteSide-0.1.0.dist-info/RECORD
