Metadata-Version: 2.1
Name: DashboardServerReportWebsiteSide
Version: 0.1.0
Summary: A website monitoring tool for performance, security, SEO, and UI
Author: Unknown
Author-email: unknown@example.com
Classifier: Programming Language :: Python :: 3
Classifier: License :: OSI Approved :: MIT License
Classifier: Operating System :: OS Independent
Requires-Python: >=3.6
Requires-Dist: annotated-types==0.7.0
Requires-Dist: anyio==4.6.2.post1
Requires-Dist: appdirs==1.4.4
Requires-Dist: apturl==0.5.2
Requires-Dist: attrs==24.2.0
Requires-Dist: bcrypt==3.2.0
Requires-Dist: beautifulsoup4==4.12.3
Requires-Dist: blinker==1.9.0
Requires-Dist: Brlapi==0.8.3
Requires-Dist: build==1.2.2.post1
Requires-Dist: CacheControl==0.12.10
Requires-Dist: cachy==0.3.0
Requires-Dist: certifi==2024.8.30
Requires-Dist: chardet==4.0.0
Requires-Dist: charset-normalizer==3.4.0
Requires-Dist: cleo==0.8.1
Requires-Dist: click==8.1.7
Requires-Dist: clikit==0.6.2
Requires-Dist: colorama==0.4.4
Requires-Dist: command-not-found==0.3
Requires-Dist: contourpy==1.3.1
Requires-Dist: crashtest==0.3.1
Requires-Dist: cryptography==3.4.8
Requires-Dist: cupshelpers==1.0
Requires-Dist: cycler==0.12.1
Requires-Dist: dbus-python==1.2.18
Requires-Dist: defer==1.0.6
Requires-Dist: distlib==0.3.4
Requires-Dist: distro==1.7.0
Requires-Dist: distro-info==1.1+ubuntu0.2
Requires-Dist: docutils==0.21.2
Requires-Dist: duplicity==0.8.21
Requires-Dist: et_xmlfile==2.0.0
Requires-Dist: exceptiongroup==1.2.2
Requires-Dist: fastapi==0.115.6
Requires-Dist: fasteners==0.14.1
Requires-Dist: filelock==3.6.0
Requires-Dist: Flask==3.1.0
Requires-Dist: Flask-Cors==5.0.0
Requires-Dist: fonttools==4.55.3
Requires-Dist: future==0.18.2
Requires-Dist: gyp==0.1
Requires-Dist: h11==0.14.0
Requires-Dist: html5lib==1.1
Requires-Dist: httplib2==0.20.2
Requires-Dist: idna==3.10
Requires-Dist: importlib-metadata==4.6.4
Requires-Dist: itsdangerous==2.2.0
Requires-Dist: jeepney==0.7.1
Requires-Dist: Jinja2==3.1.4
Requires-Dist: keyring==23.5.0
Requires-Dist: kiwisolver==1.4.7
Requires-Dist: language-selector==0.1
Requires-Dist: launchpadlib==1.10.16
Requires-Dist: lazr.restfulclient==0.14.4
Requires-Dist: lazr.uri==1.0.6
Requires-Dist: libsass==0.20.1
Requires-Dist: lockfile==0.12.2
Requires-Dist: louis==3.20.0
Requires-Dist: lxml==5.3.0
Requires-Dist: macaroonbakery==1.3.1
Requires-Dist: Mako==1.1.3
Requires-Dist: markdown-it-py==3.0.0
Requires-Dist: MarkupSafe==3.0.2
Requires-Dist: matplotlib==3.10.0
Requires-Dist: mdurl==0.1.2
Requires-Dist: monotonic==1.6
Requires-Dist: more-itertools==8.10.0
Requires-Dist: msgpack==1.0.3
Requires-Dist: netifaces==0.11.0
Requires-Dist: networkx==3.4.2
Requires-Dist: nh3==0.2.19
Requires-Dist: numpy==2.1.3
Requires-Dist: oauthlib==3.2.0
Requires-Dist: olefile==0.46
Requires-Dist: openpyxl==3.1.5
Requires-Dist: outcome==1.3.0.post0
Requires-Dist: package_server_report_website_side==2.0.0
Requires-Dist: packaging==24.2
Requires-Dist: pandas==2.2.3
Requires-Dist: paramiko==2.9.3
Requires-Dist: pastel==0.2.1
Requires-Dist: pexpect==4.8.0
Requires-Dist: Pillow==9.0.1
Requires-Dist: pkginfo==1.12.0
Requires-Dist: platformdirs==2.5.1
Requires-Dist: poetry==1.1.12
Requires-Dist: poetry-core==1.0.7
Requires-Dist: protobuf==3.12.4
Requires-Dist: psutil==6.1.0
Requires-Dist: psycopg2==2.9.10
Requires-Dist: ptyprocess==0.7.0
Requires-Dist: pycairo==1.20.1
Requires-Dist: pycups==2.0.1
Requires-Dist: pydantic==2.10.3
Requires-Dist: pydantic_core==2.27.1
Requires-Dist: pyee==11.1.1
Requires-Dist: Pygments==2.18.0
Requires-Dist: PyGObject==3.42.1
Requires-Dist: PyJWT==2.3.0
Requires-Dist: pylev==1.2.0
Requires-Dist: pymacaroons==0.13.0
Requires-Dist: PyNaCl==1.5.0
Requires-Dist: pyparsing==2.4.7
Requires-Dist: pyppeteer==2.0.0
Requires-Dist: pyproject_hooks==1.2.0
Requires-Dist: pyRFC3339==1.1
Requires-Dist: PySocks==1.7.1
Requires-Dist: python-apt==2.4.0+ubuntu4
Requires-Dist: python-dateutil==2.9.0.post0
Requires-Dist: python-debian==0.1.43+ubuntu1.1
Requires-Dist: pytz==2022.1
Requires-Dist: pyxdg==0.27
Requires-Dist: PyYAML==6.0.2
Requires-Dist: readme_renderer==44.0
Requires-Dist: reportlab==3.6.8
Requires-Dist: requests==2.32.3
Requires-Dist: requests-toolbelt==1.0.0
Requires-Dist: rfc3986==2.0.0
Requires-Dist: rich==13.9.4
Requires-Dist: schedule==1.2.2
Requires-Dist: SecretStorage==3.3.1
Requires-Dist: selenium==4.27.1
Requires-Dist: shellingham==1.4.0
Requires-Dist: six==1.16.0
Requires-Dist: sniffio==1.3.1
Requires-Dist: sortedcontainers==2.4.0
Requires-Dist: soupsieve==2.6
Requires-Dist: starlette==0.41.3
Requires-Dist: systemd-python==234
Requires-Dist: test-srver-report001==0.1
Requires-Dist: tomli==2.2.1
Requires-Dist: tomlkit==0.9.2
Requires-Dist: tqdm==4.67.1
Requires-Dist: trio==0.27.0
Requires-Dist: trio-websocket==0.11.1
Requires-Dist: twine==6.0.1
Requires-Dist: typing_extensions==4.12.2
Requires-Dist: tzdata==2024.2
Requires-Dist: ubuntu-drivers-common==0.0.0
Requires-Dist: ubuntu-pro-client==8001
Requires-Dist: ufw==0.36.1
Requires-Dist: unattended-upgrades==0.1
Requires-Dist: urllib3==2.2.3
Requires-Dist: usb-creator==0.3.7
Requires-Dist: uvicorn==0.32.1
Requires-Dist: virtualenv==20.13.0+ds
Requires-Dist: wadllib==1.3.6
Requires-Dist: webencodings==0.5.1
Requires-Dist: websocket-client==1.8.0
Requires-Dist: websockets==10.4
Requires-Dist: Werkzeug==3.1.3
Requires-Dist: wkhtmltopdf==0.2
Requires-Dist: wsproto==1.2.0
Requires-Dist: xdg==5
Requires-Dist: xkit==0.0.0
Requires-Dist: zipp==1.0.0
